geobuffers/GeoJitter.py
geobuffers/__init__.py
geobuffers/interface.py
geobuffers/shapes.py
geobuffers/utils.py
geobuffers-0.1.2.dist-info/LICENSE
geobuffers-0.1.2.dist-info/METADATA
geobuffers-0.1.2.dist-info/WHEEL
geobuffers-0.1.2.dist-info/top_level.txt
geobuffers-0.1.2.dist-info/RECORD
