Metadata-Version: 2.1
Name: geobuffers
Version: 0.1.2
Summary: geobuffers - a minipackage for computing areas around points
Author: Mikolaj Czerkawski
Author-email: Mikolaj Czerkawski <mczerkawski96@gmail.com>
Project-URL: Homepage, https://github.com/mikonvergence/geobuffers
Project-URL: Issues, https://github.com/mikonvergence/geobuffers/issues
Classifier: Programming Language :: Python :: 3
Classifier: Operating System :: OS Independent
Requires-Python: >=3
License-File: LICENSE
Requires-Dist: shapely
Requires-Dist: pyproj
